torseeker/__init__.py
torseeker/torseeker.py
torseeker-1.0.2.dist-info/LICENSE
torseeker-1.0.2.dist-info/METADATA
torseeker-1.0.2.dist-info/WHEEL
torseeker-1.0.2.dist-info/entry_points.txt
torseeker-1.0.2.dist-info/top_level.txt
torseeker-1.0.2.dist-info/RECORD
