Metadata-Version: 2.1
Name: torseeker
Version: 1.0.2
Summary: A tool used to query information about Tor relays by using a two letter country code or via Tor IP addresses.
Home-page: http://github.com/rwprimitives/tor-seeker
Author: eldiablo
Author-email: avsarria@gmail.com
License: MIT
Project-URL: Source, http://github.com/rwprimitives/tor-seeker
Project-URL: Bug Tracker, https://github.com/rwprimitives/tor-seeker/issues
Keywords: tor,relay,network,ip,anonymity
Platform: any
Classifier: Development Status :: 5 - Production/Stable
Classifier: Intended Audience :: Developers
Classifier: Intended Audience :: Information Technology
Classifier: Intended Audience :: Science/Research
Classifier: Intended Audience :: System Administrators
Classifier: Operating System :: OS Independent
Classifier: Topic :: Internet
Classifier: Topic :: Scientific/Engineering
Classifier: Topic :: System :: Networking
Classifier: License :: OSI Approved :: MIT License
Classifier: Natural Language :: English
Classifier: Programming Language :: Python :: 3 :: Only
Classifier: Programming Language :: Python :: Implementation
Classifier: Programming Language :: Python :: Implementation :: CPython
Requires-Python: >=3
License-File: LICENSE
Provides-Extra: codestyle
Requires-Dist: flake8 (<4,>=3) ; extra == 'codestyle'
